ragpy/src/dataprocessing/data_loader.py
ragpy/src/embeddings_creation/embedding_generator.py
ragpy/src/generator/generation_benchmarking.py
ragpy/src/retriever/retrieval.py
ragpy/src/retriever/retrieval_benchmarking.py
ragpy_new-0.1.17.dist-info/METADATA
ragpy_new-0.1.17.dist-info/WHEEL
ragpy_new-0.1.17.dist-info/top_level.txt
ragpy_new-0.1.17.dist-info/RECORD
