Metadata-Version: 2.1
Name: ragpy_new
Version: 0.1.17
Author: BayesLabs
Author-email: contact@bayeslabs.co
Requires-Dist: langchain ==0.1.9
Requires-Dist: sentence-transformers ==2.2.2
Requires-Dist: langchain-community ==0.0.34
Requires-Dist: datasets >=2.19.1
Requires-Dist: langchain-openai ==0.1.3
Requires-Dist: langchain-fireworks ==0.1.2
Requires-Dist: pypdf2 >=3.0.1
Requires-Dist: chardet >=5.2.0
Requires-Dist: nltk >=3.8.1
Requires-Dist: chromadb >=0.4.24
Requires-Dist: faiss-cpu >=1.8.0
Requires-Dist: InstructorEmbedding >=1.0.1
Requires-Dist: langchain-text-splitters >=0.0.2
Requires-Dist: pandas ==2.2.2
